radtract/__init__.py
radtract/features.py
radtract/parcellation.py
radtract/prediction.py
radtract/pyrad.yaml
radtract/pyrad_D.yaml
radtract/pyrad_nofilter.yaml
radtract/pyrad_nofilter_D.yaml
radtract/tractdensity.py
radtract/tractfiltering.py
radtract/utils.py
radtract-0.2.4.dist-info/METADATA
radtract-0.2.4.dist-info/WHEEL
radtract-0.2.4.dist-info/entry_points.txt
radtract-0.2.4.dist-info/top_level.txt
radtract-0.2.4.dist-info/RECORD
