Metadata-Version: 2.4
Name: radtract
Version: 0.2.4
Summary: Radiomic Tractometry for advanced along-tract analysis of diffusion-weighted MRI
Author-email: Peter Neher <p.neher@dkfz-heidelberg.de>
Maintainer-email: Peter Neher <p.neher@dkfz-heidelberg.de>
License: Apache License
Project-URL: Repository, https://github.com/MIC-DKFZ/radtract
Keywords: tractometry,radiomics,tractography,diffusion-weighted MRI
Classifier: Programming Language :: Python :: 3
Classifier: Operating System :: OS Independent
Classifier: Development Status :: 5 - Production/Stable
Requires-Python: >=3.10
Requires-Dist: numpy<2.0,>=1.26
Requires-Dist: pandas
Requires-Dist: argparse
Requires-Dist: scikit-image
Requires-Dist: scikit-learn
Requires-Dist: nibabel
Requires-Dist: vtk
Requires-Dist: dipy
Requires-Dist: pyradiomics
Requires-Dist: mirp; python_version >= "3.11"
Requires-Dist: cmdint
Requires-Dist: fury
Requires-Dist: seaborn
